{
    "Agm110" : 9.372e-3,
    "Alphan_Telab_13c" : 0,
    "Co60" : 6.606e-2,
    "B8_Solar_Nue" : 1338,
    "Te130_0n2b" : 0,
    "B8_Solar_Numu" : 0,
    "Te130_2n2b" : 6.33e6,
    "Tl208_Av" : 1.5e6,
    "Tl208_Hdropes": 2.32e6,
    "Na22" : 1.579e-1,
    "Te130_0n2b_N2" : 0,
    "Te130_0n2b_N3" : 0,
    "Ac228" : 49190,
    "Te130_0n2b_N1" : 0,
    "Te130_0n2b_N7" : 0,
    "Rn222" : 390314,
    "Bi210" : 427368,
    "Bipo212-pure" : 18015,
    "Bi214_Exwater" : 1.32e8,
    "Po210" : 1.74e7,
    "Po210_Av_Outerdust" : 2.69e10,
    "Pa234m" : 390314,
    "Po212"  : 31482,
    "Po214" : 390314,
    "Bi210_Av_Innerdust" : 2.14e10,
    "Bi212tl208" : 0,
    "Bipo214-pure" : 7.55e5,
    "Alphan_Telab_Avin_Av_13c" : 0,
    "Pmt_Betagammas" : 7.18e4,
    "C14"  : 3.78E9,
    "Tl208_Exwater" : 3.92e6,
    "Bi214tl210" : 0,
    "Alphan_Telab_Avin_Ls_13c" : 0,
    "Tl210" : 82,
    "Po210_Av_Innerdust" : 2.25e10,    
    "Alphan_Telab_Avin_Av_18o" : 0,
    "Te130_2n2b_Etail" : 0,
    "Rn220" : 49190,
    "Ar39" : 79243,
    "Bi210_Av_Outerdust" : 2.60e10,   
    "Bi214_Av" : 1.28e7,    
    "Bi214_Hdropes" : 4.06e6
}